tests/test_methods/__init__.py
tests/test_methods/test_address.py
tests/test_methods/test_base.py
tests/test_methods/test_candidatebio.py
tests/test_methods/test_candidates.py
tests/test_methods/test_committee.py
tests/test_methods/test_containers.py
tests/test_methods/test_district.py
tests/test_methods/test_elections.py
tests/test_methods/test_leadership.py
tests/test_methods/test_local.py
tests/test_methods/test_measure.py
tests/test_methods/test_npat.py
tests/test_methods/test_office.py
tests/test_methods/test_officials.py
tests/test_methods/test_ratings.py
tests/test_methods/test_states.py
tests/test_methods/test_utils.py
tests/test_methods/test_votes.py
votesmart/__init__.py
votesmart/api.py
votesmart/exceptions.py
votesmart/votesmart.py
votesmart/methods/__init__.py
votesmart/methods/address.py
votesmart/methods/base.py
votesmart/methods/candidatebio.py
votesmart/methods/candidates.py
votesmart/methods/committee.py
votesmart/methods/containers.py
votesmart/methods/district.py
votesmart/methods/elections.py
votesmart/methods/leadership.py
votesmart/methods/local.py
votesmart/methods/measure.py
votesmart/methods/npat.py
votesmart/methods/office.py
votesmart/methods/officials.py
votesmart/methods/ratings.py
votesmart/methods/states.py
votesmart/methods/utils.py
votesmart/methods/votes.py
py_votesmart_aqadir-0.4.41.dist-info/AUTHORS
py_votesmart_aqadir-0.4.41.dist-info/LICENSE.txt
py_votesmart_aqadir-0.4.41.dist-info/METADATA
py_votesmart_aqadir-0.4.41.dist-info/WHEEL
py_votesmart_aqadir-0.4.41.dist-info/top_level.txt
py_votesmart_aqadir-0.4.41.dist-info/RECORD
