Metadata-Version: 2.1
Name: py-votesmart-aqadir
Version: 0.4.41
Summary: Libraries for interacting with the Project Vote Smart API
Home-page: https://github.com/DarthQadir/py-votesmart-aqadir
Author: Nathan Danielsen <nathan.danielsen@gmail.com>
Author-email: nathan.danielsen@gmail.com
License: BSD
Platform: any
Classifier: Development Status :: 3 - Alpha
Classifier: Intended Audience :: Developers
Classifier: License :: OSI Approved :: BSD License
Classifier: Natural Language :: English
Classifier: Operating System :: OS Independent
Classifier: Programming Language :: Python
Classifier: Topic :: Software Development :: Libraries :: Python Modules
Classifier: Programming Language :: Python
Classifier: Programming Language :: Python :: 2.7
Classifier: Programming Language :: Python :: 3.4
Classifier: Programming Language :: Python :: 3.5
Classifier: Programming Language :: Python :: 3.6
License-File: LICENSE.txt
License-File: AUTHORS
Requires-Dist: simplejson (>=1.8)
Requires-Dist: requests (>=2.20.0)
